[
    {
        "id": 0,
        "poolId": 0,
        "lpAddress": "0x63da4DB6Ef4e7C62168aB03982399F9588fCd198",
        "totalSupply": 127641350978378215879958266,
        "totalStaked": 127537233368079786329494676,
        "totalStakedInUSD": 48461121.731546134,
        "totalRewardRate": 332640.0,
        "allocPoint": 11,
        "apr": 40.65470467132676,
        "apr2": 0,
        "chefVersion": "v1"
    },
    {
        "id": 1,
        "poolId": 1,
        "lpAddress": "0x20F8AeFB5697B77E0BB835A8518BE70775cdA1b0",
        "totalSupply": 5597853134980682919200,
        "totalStaked": 5595094902534945398857,
        "totalStakedInUSD": 41800150.874161795,
        "totalRewardRate": 332640.0,
        "allocPoint": 11,
        "apr": 47.133145475201125,
        "apr2": 0,
        "chefVersion": "v1"
    },
    {
        "id": 2,
        "poolId": 2,
        "lpAddress": "0x03B666f3488a7992b2385B12dF7f35156d7b29cD",
        "totalSupply": 4168478542194202699147,
        "totalStaked": 4165403350769728699763,
        "totalStakedInUSD": 32790797.41199955,
        "totalRewardRate": 332640.0,
        "allocPoint": 11,
        "apr": 60.08309487820669,
        "apr2": 0,
        "chefVersion": "v1"
    },
    {
        "id": 3,
        "poolId": 3,
        "lpAddress": "0x2fe064B6c7D274082aa5d2624709bC9AE7D16C77",
        "totalSupply": 77608685296296,
        "totalStaked": 77511419406597,
        "totalStakedInUSD": 160640516.88112864,
        "totalRewardRate": 302400.0,
        "allocPoint": 10,
        "apr": 11.14952832283571,
        "apr2": 0,
        "chefVersion": "v1"
    },
    {
        "id": 4,
        "poolId": 4,
        "lpAddress": "0xbc8A244e8fb683ec1Fd6f88F3cc6E565082174Eb",
        "totalSupply": 363925495306086507262,
        "totalStaked": 363635773260758558563,
        "totalStakedInUSD": 48166563.13090423,
        "totalRewardRate": 332640.0,
        "allocPoint": 11,
        "apr": 40.90332512790679,
        "apr2": 0,
        "chefVersion": "v1"
    },
    {
        "id": 5,
        "poolId": 5,
        "lpAddress": "0x84b123875F0F36B966d0B6Ca14b31121bd9676AD",
        "totalSupply": 885084688985834887883303785,
        "totalStaked": 868561310631256670424603579,
        "totalStakedInUSD": 25486618.29426598,
        "totalRewardRate": 665280.0,
        "allocPoint": 22,
        "apr": 154.60447276996933,
        "apr2": 0,
        "chefVersion": "v1"
    },
    {
        "id": 6,
        "poolId": 6,
        "lpAddress": "0x5eeC60F348cB1D661E4A5122CF4638c7DB7A886e",
        "totalSupply": 10085129122646008311131,
        "totalStaked": 24712978301219805248,
        "totalStakedInUSD": 9009.192896369961,
        "totalRewardRate": 0.0,
        "allocPoint": 0,
        "apr": 0.0,
        "apr2": 0,
        "chefVersion": "v1"
    },
    {
        "id": 7,
        "poolId": 0,
        "lpAddress": "0x5eeC60F348cB1D661E4A5122CF4638c7DB7A886e",
        "totalSupply": 10085129122646008311131,
        "totalStaked": 9850748170896517611504,
        "totalStakedInUSD": 3591120.8015259667,
        "totalRewardRate": 29030.4,
        "allocPoint": 4,
        "apr": 47.879852783566534,
        "apr2": 14.479232174196376,
        "chefVersion": "v2"
    },
    {
        "id": 8,
        "poolId": 1,
        "lpAddress": "0xd1654a7713617d41A8C9530Fb9B948d00e162194",
        "totalSupply": 808848768379254321318727,
        "totalStaked": 795064175193989506800589,
        "totalStakedInUSD": 6247964.732939366,
        "totalRewardRate": 217728.0,
        "allocPoint": 30,
        "apr": 206.39801437888735,
        "apr2": 8.322177552756244,
        "chefVersion": "v2"
    },
    {
        "id": 9,
        "poolId": 2,
        "lpAddress": "0xdF8CbF89ad9b7dAFdd3e37acEc539eEcC8c47914",
        "totalSupply": 67874405140636330324203462,
        "totalStaked": 66816028924284178945095442,
        "totalStakedInUSD": 3891469.9456919204,
        "totalRewardRate": 29030.4,
        "allocPoint": 4,
        "apr": 44.18441815165931,
        "apr2": 9.986159161186347,
        "chefVersion": "v2"
    },
    {
        "id": 10,
        "poolId": 3,
        "lpAddress": "0xa9eded3E339b9cd92bB6DEF5c5379d678131fF90",
        "totalSupply": 494683500358544434885246363,
        "totalStaked": 489686771587936100661266149,
        "totalStakedInUSD": 3488532.5130485347,
        "totalRewardRate": 29030.4,
        "allocPoint": 4,
        "apr": 49.28786951588735,
        "apr2": 11.139594687249529,
        "chefVersion": "v2"
    },
    {
        "id": 11,
        "poolId": 4,
        "lpAddress": "0x61C9E05d1Cdb1b70856c7a2c53fA9c220830633c",
        "totalSupply": 210703791183180643,
        "totalStaked": 208353655552814304,
        "totalStakedInUSD": 9943267.326860355,
        "totalRewardRate": 304819.2,
        "allocPoint": 42,
        "apr": 181.56954463309845,
        "apr2": 0.0,
        "chefVersion": "v2"
    },
    {
        "id": 12,
        "poolId": 5,
        "lpAddress": "0x6443532841a5279cb04420E61Cf855cBEb70dc8C",
        "totalSupply": 50132082633622976975820497,
        "totalStaked": 50100491171913699113005088,
        "totalStakedInUSD": 2790392.885154615,
        "totalRewardRate": 29030.4,
        "allocPoint": 4,
        "apr": 61.61939998479442,
        "apr2": 0.0,
        "chefVersion": "v2"
    },
    {
        "id": 13,
        "poolId": 6,
        "lpAddress": "0x7be4a49AA41B34db70e539d4Ae43c7fBDf839DfA",
        "totalSupply": 25790273539874401974218615,
        "totalStaked": 25763082752450482602868885,
        "totalStakedInUSD": 3494670.5170835303,
        "totalRewardRate": 29030.4,
        "allocPoint": 4,
        "apr": 49.20130079918403,
        "apr2": 0.0,
        "chefVersion": "v2"
    },
    {
        "id": 14,
        "poolId": 7,
        "lpAddress": "0x3dC236Ea01459F57EFc737A12BA3Bb5F3BFfD071",
        "totalSupply": 370490584754800686709793983,
        "totalStaked": 369461156490590296356851178,
        "totalStakedInUSD": 3250457.867417085,
        "totalRewardRate": 29030.4,
        "allocPoint": 4,
        "apr": 52.89788156574308,
        "apr2": 0.0,
        "chefVersion": "v2"
    },
    {
        "id": 15,
        "poolId": 8,
        "lpAddress": "0x48887cEEA1b8AD328d5254BeF774Be91B90FaA09",
        "totalSupply": 318639188662238517283582729,
        "totalStaked": 179694638559883746553605530,
        "totalStakedInUSD": 1121416.6743040925,
        "totalRewardRate": 29030.4,
        "allocPoint": 4,
        "apr": 153.32600205161697,
        "apr2": 105.86003494387101,
        "chefVersion": "v2"
    }
]