[
    {
        "id": 0,
        "poolId": 0,
        "lpAddress": "0x63da4DB6Ef4e7C62168aB03982399F9588fCd198",
        "totalSupply": 114417597593963643962231601,
        "totalStaked": 114009692183148095521752629,
        "totalStakedInUSD": 53988024.06068383,
        "totalRewardRate": 332640.0,
        "allocPoint": 11,
        "apr": 58.961017087923125,
        "apr2": 0,
        "chefVersion": "v1"
    },
    {
        "id": 1,
        "poolId": 1,
        "lpAddress": "0x20F8AeFB5697B77E0BB835A8518BE70775cdA1b0",
        "totalSupply": 5222172431760501216863,
        "totalStaked": 5212728525484282872769,
        "totalStakedInUSD": 43391658.32302421,
        "totalRewardRate": 332640.0,
        "allocPoint": 11,
        "apr": 73.35946428892625,
        "apr2": 0,
        "chefVersion": "v1"
    },
    {
        "id": 2,
        "poolId": 2,
        "lpAddress": "0x03B666f3488a7992b2385B12dF7f35156d7b29cD",
        "totalSupply": 5044530359498482571745,
        "totalStaked": 5038385765254920717285,
        "totalStakedInUSD": 44219989.307553306,
        "totalRewardRate": 332640.0,
        "allocPoint": 11,
        "apr": 71.98529124568235,
        "apr2": 0,
        "chefVersion": "v1"
    },
    {
        "id": 3,
        "poolId": 3,
        "lpAddress": "0x2fe064B6c7D274082aa5d2624709bC9AE7D16C77",
        "totalSupply": 75924029037861,
        "totalStaked": 75846868435887,
        "totalStakedInUSD": 157094602.2504252,
        "totalRewardRate": 302400.0,
        "allocPoint": 10,
        "apr": 18.42079846726455,
        "apr2": 0,
        "chefVersion": "v1"
    },
    {
        "id": 4,
        "poolId": 4,
        "lpAddress": "0xbc8A244e8fb683ec1Fd6f88F3cc6E565082174Eb",
        "totalSupply": 344450665024355866027,
        "totalStaked": 344428758725488998678,
        "totalStakedInUSD": 55460212.658479504,
        "totalRewardRate": 332640.0,
        "allocPoint": 11,
        "apr": 57.39589980996034,
        "apr2": 0,
        "chefVersion": "v1"
    },
    {
        "id": 5,
        "poolId": 5,
        "lpAddress": "0x84b123875F0F36B966d0B6Ca14b31121bd9676AD",
        "totalSupply": 770333177236056566100595298,
        "totalStaked": 736142926328310978877290969,
        "totalStakedInUSD": 30717096.326219086,
        "totalRewardRate": 665280.0,
        "allocPoint": 22,
        "apr": 207.2584449636355,
        "apr2": 0,
        "chefVersion": "v1"
    },
    {
        "id": 6,
        "poolId": 6,
        "lpAddress": "0x5eeC60F348cB1D661E4A5122CF4638c7DB7A886e",
        "totalSupply": 9783167929782588833511,
        "totalStaked": 26404725340461237511,
        "totalStakedInUSD": 13956.54637729203,
        "totalRewardRate": 0.0,
        "allocPoint": 0,
        "apr": 0.0,
        "apr2": 0,
        "chefVersion": "v1"
    },
    {
        "id": 7,
        "poolId": 0,
        "lpAddress": "0x5eeC60F348cB1D661E4A5122CF4638c7DB7A886e",
        "totalSupply": 9783167929782588833511,
        "totalStaked": 9715627405578597245038,
        "totalStakedInUSD": 5135315.8467687555,
        "totalRewardRate": 65318.399999999994,
        "allocPoint": 9,
        "apr": 121.71841975346808,
        "apr2": 17.294559962064955,
        "chefVersion": "v2"
    },
    {
        "id": 8,
        "poolId": 1,
        "lpAddress": "0xd1654a7713617d41A8C9530Fb9B948d00e162194",
        "totalSupply": 651010739261845225057897,
        "totalStaked": 645042580822212090118013,
        "totalStakedInUSD": 8394004.780706782,
        "totalRewardRate": 210470.4,
        "allocPoint": 29,
        "apr": 239.94391550038256,
        "apr2": 10.580531004725794,
        "chefVersion": "v2"
    },
    {
        "id": 9,
        "poolId": 2,
        "lpAddress": "0xdF8CbF89ad9b7dAFdd3e37acEc539eEcC8c47914",
        "totalSupply": 54122358661307972519085538,
        "totalStaked": 54116234302047031825081808,
        "totalStakedInUSD": 3567125.3844711874,
        "totalRewardRate": 29030.4,
        "allocPoint": 4,
        "apr": 77.87939555222549,
        "apr2": 0.0,
        "chefVersion": "v2"
    },
    {
        "id": 10,
        "poolId": 3,
        "lpAddress": "0xa9eded3E339b9cd92bB6DEF5c5379d678131fF90",
        "totalSupply": 445164976454457434236058071,
        "totalStaked": 438065539357198268569589329,
        "totalStakedInUSD": 3480658.4343377305,
        "totalRewardRate": 29030.4,
        "allocPoint": 4,
        "apr": 79.81408519175035,
        "apr2": 0.0,
        "chefVersion": "v2"
    },
    {
        "id": 11,
        "poolId": 4,
        "lpAddress": "0x61C9E05d1Cdb1b70856c7a2c53fA9c220830633c",
        "totalSupply": 191507910161833548,
        "totalStaked": 186962300943850340,
        "totalStakedInUSD": 11288444.298330028,
        "totalRewardRate": 304819.2,
        "allocPoint": 42,
        "apr": 258.4021673250842,
        "apr2": 0.0,
        "chefVersion": "v2"
    },
    {
        "id": 12,
        "poolId": 5,
        "lpAddress": "0x6443532841a5279cb04420E61Cf855cBEb70dc8C",
        "totalSupply": 42649253835116746819501140,
        "totalStaked": 40210162301092823462480537,
        "totalStakedInUSD": 2883883.345536809,
        "totalRewardRate": 29030.4,
        "allocPoint": 4,
        "apr": 96.33037661927516,
        "apr2": 0.0,
        "chefVersion": "v2"
    },
    {
        "id": 13,
        "poolId": 6,
        "lpAddress": "0x7be4a49AA41B34db70e539d4Ae43c7fBDf839DfA",
        "totalSupply": 20865626741640350625750898,
        "totalStaked": 20863078444603571098879026,
        "totalStakedInUSD": 3373384.880727487,
        "totalRewardRate": 29030.4,
        "allocPoint": 4,
        "apr": 82.35217107563068,
        "apr2": 0.0,
        "chefVersion": "v2"
    },
    {
        "id": 14,
        "poolId": 7,
        "lpAddress": "0x3dC236Ea01459F57EFc737A12BA3Bb5F3BFfD071",
        "totalSupply": 307553781968401530612809753,
        "totalStaked": 307524048530875189095754097,
        "totalStakedInUSD": 3437143.6912398613,
        "totalRewardRate": 29030.4,
        "allocPoint": 4,
        "apr": 80.82454321291549,
        "apr2": 0.0,
        "chefVersion": "v2"
    }
]