[
    {
        "id": 0,
        "poolId": 0,
        "lpAddress": "0x63da4DB6Ef4e7C62168aB03982399F9588fCd198",
        "totalSupply": 121282472647389935261399231,
        "totalStaked": 121176669840704996737252124,
        "totalStakedInUSD": 44045993.31796074,
        "totalRewardRate": 332640.0,
        "allocPoint": 11,
        "apr": 36.51366135483887,
        "apr2": 0,
        "chefVersion": "v1"
    },
    {
        "id": 1,
        "poolId": 1,
        "lpAddress": "0x20F8AeFB5697B77E0BB835A8518BE70775cdA1b0",
        "totalSupply": 5459458753920115457930,
        "totalStaked": 5458533403218881696306,
        "totalStakedInUSD": 39564821.940409124,
        "totalRewardRate": 332640.0,
        "allocPoint": 11,
        "apr": 40.64925368479703,
        "apr2": 0,
        "chefVersion": "v1"
    },
    {
        "id": 2,
        "poolId": 2,
        "lpAddress": "0x03B666f3488a7992b2385B12dF7f35156d7b29cD",
        "totalSupply": 3936231498646791231288,
        "totalStaked": 3933639099314704364368,
        "totalStakedInUSD": 30037567.30464509,
        "totalRewardRate": 332640.0,
        "allocPoint": 11,
        "apr": 53.54230146995977,
        "apr2": 0,
        "chefVersion": "v1"
    },
    {
        "id": 3,
        "poolId": 3,
        "lpAddress": "0x2fe064B6c7D274082aa5d2624709bC9AE7D16C77",
        "totalSupply": 72823127626934,
        "totalStaked": 72791354698263,
        "totalStakedInUSD": 151008758.9107135,
        "totalRewardRate": 302400.0,
        "allocPoint": 10,
        "apr": 9.682042140232511,
        "apr2": 0,
        "chefVersion": "v1"
    },
    {
        "id": 4,
        "poolId": 4,
        "lpAddress": "0xbc8A244e8fb683ec1Fd6f88F3cc6E565082174Eb",
        "totalSupply": 368404858136975771963,
        "totalStaked": 368386238431237011378,
        "totalStakedInUSD": 47762127.074339375,
        "totalRewardRate": 332640.0,
        "allocPoint": 11,
        "apr": 33.67271481745998,
        "apr2": 0,
        "chefVersion": "v1"
    },
    {
        "id": 5,
        "poolId": 5,
        "lpAddress": "0x84b123875F0F36B966d0B6Ca14b31121bd9676AD",
        "totalSupply": 881386258917112118152170097,
        "totalStaked": 876288716147446339789779452,
        "totalStakedInUSD": 22495299.232295163,
        "totalRewardRate": 665280.0,
        "allocPoint": 22,
        "apr": 142.9881387610618,
        "apr2": 0,
        "chefVersion": "v1"
    },
    {
        "id": 6,
        "poolId": 6,
        "lpAddress": "0x5eeC60F348cB1D661E4A5122CF4638c7DB7A886e",
        "totalSupply": 9806744128266541351313,
        "totalStaked": 24476168167527771029,
        "totalStakedInUSD": 8653.702908515925,
        "totalRewardRate": 0.0,
        "allocPoint": 0,
        "apr": 0.0,
        "apr2": 0,
        "chefVersion": "v1"
    },
    {
        "id": 7,
        "poolId": 0,
        "lpAddress": "0x5eeC60F348cB1D661E4A5122CF4638c7DB7A886e",
        "totalSupply": 9806744128266541351313,
        "totalStaked": 9489225034166174219908,
        "totalStakedInUSD": 3354975.0808898862,
        "totalRewardRate": 29030.4,
        "allocPoint": 4,
        "apr": 41.83608541893363,
        "apr2": 14.752198165135733,
        "chefVersion": "v2"
    },
    {
        "id": 8,
        "poolId": 1,
        "lpAddress": "0xd1654a7713617d41A8C9530Fb9B948d00e162194",
        "totalSupply": 911455642131687508539107,
        "totalStaked": 900583998271629520388654,
        "totalStakedInUSD": 6245496.89559523,
        "totalRewardRate": 217728.0,
        "allocPoint": 30,
        "apr": 168.55227023028488,
        "apr2": 7.9246308275785164,
        "chefVersion": "v2"
    },
    {
        "id": 9,
        "poolId": 2,
        "lpAddress": "0xdF8CbF89ad9b7dAFdd3e37acEc539eEcC8c47914",
        "totalSupply": 68998023504400698779782683,
        "totalStaked": 67979800978600113861526630,
        "totalStakedInUSD": 3580034.92029614,
        "totalRewardRate": 29030.4,
        "allocPoint": 4,
        "apr": 39.206048875884306,
        "apr2": 9.433909026238023,
        "chefVersion": "v2"
    },
    {
        "id": 10,
        "poolId": 3,
        "lpAddress": "0xa9eded3E339b9cd92bB6DEF5c5379d678131fF90",
        "totalSupply": 428519923435838666928532564,
        "totalStaked": 418967128435410340411764807,
        "totalStakedInUSD": 2892824.826417013,
        "totalRewardRate": 29030.4,
        "allocPoint": 4,
        "apr": 48.51971083100408,
        "apr2": 11.674997891476352,
        "chefVersion": "v2"
    },
    {
        "id": 11,
        "poolId": 4,
        "lpAddress": "0x61C9E05d1Cdb1b70856c7a2c53fA9c220830633c",
        "totalSupply": 170412828247107754,
        "totalStaked": 168086277604743783,
        "totalStakedInUSD": 7257502.666457536,
        "totalRewardRate": 304819.2,
        "allocPoint": 42,
        "apr": 203.06844108617386,
        "apr2": 0.0,
        "chefVersion": "v2"
    },
    {
        "id": 12,
        "poolId": 5,
        "lpAddress": "0x6443532841a5279cb04420E61Cf855cBEb70dc8C",
        "totalSupply": 46810062639629865456217375,
        "totalStaked": 46779288210969559726098352,
        "totalStakedInUSD": 2545005.5855113356,
        "totalRewardRate": 29030.4,
        "allocPoint": 4,
        "apr": 55.15077250186172,
        "apr2": 0.0,
        "chefVersion": "v2"
    },
    {
        "id": 13,
        "poolId": 6,
        "lpAddress": "0x7be4a49AA41B34db70e539d4Ae43c7fBDf839DfA",
        "totalSupply": 25870245609332012511790002,
        "totalStaked": 25869606209146828775253386,
        "totalStakedInUSD": 3346144.2479390805,
        "totalRewardRate": 29030.4,
        "allocPoint": 4,
        "apr": 41.94649532785426,
        "apr2": 0.0,
        "chefVersion": "v2"
    },
    {
        "id": 14,
        "poolId": 7,
        "lpAddress": "0x3dC236Ea01459F57EFc737A12BA3Bb5F3BFfD071",
        "totalSupply": 379632556912637581462873517,
        "totalStaked": 333630698906506937044488129,
        "totalStakedInUSD": 2822803.744537595,
        "totalRewardRate": 29030.4,
        "allocPoint": 4,
        "apr": 49.72326692357259,
        "apr2": 0.0,
        "chefVersion": "v2"
    },
    {
        "id": 15,
        "poolId": 8,
        "lpAddress": "0x48887cEEA1b8AD328d5254BeF774Be91B90FaA09",
        "totalSupply": 330444366337276115128119393,
        "totalStaked": 191484528448192168313526228,
        "totalStakedInUSD": 1136886.2995675376,
        "totalRewardRate": 29030.4,
        "allocPoint": 4,
        "apr": 123.45915692351514,
        "apr2": 103.86912522100872,
        "chefVersion": "v2"
    },
    {
        "id": 16,
        "poolId": 9,
        "lpAddress": "0xd62f9ec4C4d323A0C111d5e78b77eA33A2AA862f",
        "totalSupply": 55909260458672614049522293,
        "totalStaked": 55887748036492411659069596,
        "totalStakedInUSD": 168477.70995768587,
        "totalRewardRate": 0.0,
        "allocPoint": 0,
        "apr": 0.0,
        "apr2": 1700.4785987042296,
        "chefVersion": "v2"
    }
]