[
    {
        "id": 0,
        "poolId": 0,
        "lpAddress": "0x63da4DB6Ef4e7C62168aB03982399F9588fCd198",
        "totalSupply": 48124099815930691543011979,
        "totalStaked": 47755104858634838654199486,
        "totalStakedInUSD": 19378569.81510745,
        "totalRewardRate": 393120.0,
        "allocPoint": 13,
        "apr": 57.956907393791724,
        "apr2": 0,
        "chefVersion": "v1"
    },
    {
        "id": 1,
        "poolId": 1,
        "lpAddress": "0x20F8AeFB5697B77E0BB835A8518BE70775cdA1b0",
        "totalSupply": 1701123722955905687134,
        "totalStaked": 1700086360057766792647,
        "totalStakedInUSD": 10891381.164623264,
        "totalRewardRate": 393120.0,
        "allocPoint": 13,
        "apr": 103.12025253935359,
        "apr2": 0,
        "chefVersion": "v1"
    },
    {
        "id": 2,
        "poolId": 2,
        "lpAddress": "0x03B666f3488a7992b2385B12dF7f35156d7b29cD",
        "totalSupply": 1483028076025205705961,
        "totalStaked": 1481426953284885635095,
        "totalStakedInUSD": 10010618.134212038,
        "totalRewardRate": 393120.0,
        "allocPoint": 13,
        "apr": 112.19306951285621,
        "apr2": 0,
        "chefVersion": "v1"
    },
    {
        "id": 3,
        "poolId": 3,
        "lpAddress": "0x2fe064B6c7D274082aa5d2624709bC9AE7D16C77",
        "totalSupply": 23050730170919,
        "totalStaked": 22976699728058,
        "totalStakedInUSD": 47554991.27102211,
        "totalRewardRate": 362880.0,
        "allocPoint": 12,
        "apr": 21.800613359820865,
        "apr2": 0,
        "chefVersion": "v1"
    },
    {
        "id": 4,
        "poolId": 4,
        "lpAddress": "0xbc8A244e8fb683ec1Fd6f88F3cc6E565082174Eb",
        "totalSupply": 116326054254422278067,
        "totalStaked": 116310811034472361678,
        "totalStakedInUSD": 15463126.779171295,
        "totalRewardRate": 393120.0,
        "allocPoint": 13,
        "apr": 72.6322685080191,
        "apr2": 0,
        "chefVersion": "v1"
    },
    {
        "id": 5,
        "poolId": 5,
        "lpAddress": "0x84b123875F0F36B966d0B6Ca14b31121bd9676AD",
        "totalSupply": 296465605419660240575207817,
        "totalStaked": 290315882565429650887425574,
        "totalStakedInUSD": 5101753.770102578,
        "totalRewardRate": 665280.0,
        "allocPoint": 22,
        "apr": 372.5518802688123,
        "apr2": 0,
        "chefVersion": "v1"
    },
    {
        "id": 6,
        "poolId": 6,
        "lpAddress": "0x5eeC60F348cB1D661E4A5122CF4638c7DB7A886e",
        "totalSupply": 10301561987615886791255,
        "totalStaked": 560434521381274116654,
        "totalStakedInUSD": 219398.23174865247,
        "totalRewardRate": 0.0,
        "allocPoint": 0,
        "apr": 0.0,
        "apr2": 0,
        "chefVersion": "v1"
    },
    {
        "id": 7,
        "poolId": 0,
        "lpAddress": "0x5eeC60F348cB1D661E4A5122CF4638c7DB7A886e",
        "totalSupply": 10301561987615886791255,
        "totalStaked": 6522879607652867019881,
        "totalStakedInUSD": 2553569.056205182,
        "totalRewardRate": 122774.39999999998,
        "allocPoint": 29,
        "apr": 137.36054316377383,
        "apr2": 16.09557304559223,
        "chefVersion": "v2"
    },
    {
        "id": 8,
        "poolId": 1,
        "lpAddress": "0xd1654a7713617d41A8C9530Fb9B948d00e162194",
        "totalSupply": 329301631306625342673480,
        "totalStaked": 327488455531096239842118,
        "totalStakedInUSD": 1571497.0447669514,
        "totalRewardRate": 300585.6,
        "allocPoint": 71,
        "apr": 546.4574971111145,
        "apr2": 26.154142260706383,
        "chefVersion": "v2"
    }
]