[
    {
        "id": 0,
        "poolId": 0,
        "lpAddress": "0x63da4DB6Ef4e7C62168aB03982399F9588fCd198",
        "totalSupply": 121838854871467605352786315,
        "totalStaked": 121743623487708519737814178,
        "totalStakedInUSD": 43916896.03134951,
        "totalRewardRate": 332640.0,
        "allocPoint": 11,
        "apr": 34.746563854693214,
        "apr2": 0,
        "chefVersion": "v1"
    },
    {
        "id": 1,
        "poolId": 1,
        "lpAddress": "0x20F8AeFB5697B77E0BB835A8518BE70775cdA1b0",
        "totalSupply": 5494811239001487335277,
        "totalStaked": 5493919265629201148603,
        "totalStakedInUSD": 38481660.55372363,
        "totalRewardRate": 332640.0,
        "allocPoint": 11,
        "apr": 39.654245952376165,
        "apr2": 0,
        "chefVersion": "v1"
    },
    {
        "id": 2,
        "poolId": 2,
        "lpAddress": "0x03B666f3488a7992b2385B12dF7f35156d7b29cD",
        "totalSupply": 4214765514972711407289,
        "totalStaked": 4212314320054605984490,
        "totalStakedInUSD": 31115495.569228202,
        "totalRewardRate": 332640.0,
        "allocPoint": 11,
        "apr": 49.04184247550003,
        "apr2": 0,
        "chefVersion": "v1"
    },
    {
        "id": 3,
        "poolId": 3,
        "lpAddress": "0x2fe064B6c7D274082aa5d2624709bC9AE7D16C77",
        "totalSupply": 72018992888248,
        "totalStaked": 71982689170466,
        "totalStakedInUSD": 149266390.99437293,
        "totalRewardRate": 302400.0,
        "allocPoint": 10,
        "apr": 9.293702853168396,
        "apr2": 0,
        "chefVersion": "v1"
    },
    {
        "id": 4,
        "poolId": 4,
        "lpAddress": "0xbc8A244e8fb683ec1Fd6f88F3cc6E565082174Eb",
        "totalSupply": 369706641894458881741,
        "totalStaked": 369688035906904483060,
        "totalStakedInUSD": 47047887.47690916,
        "totalRewardRate": 332640.0,
        "allocPoint": 11,
        "apr": 32.434213608467374,
        "apr2": 0,
        "chefVersion": "v1"
    },
    {
        "id": 5,
        "poolId": 5,
        "lpAddress": "0x84b123875F0F36B966d0B6Ca14b31121bd9676AD",
        "totalSupply": 902348761539479417542875553,
        "totalStaked": 896415119780387763375879757,
        "totalStakedInUSD": 21632403.408958655,
        "totalRewardRate": 665280.0,
        "allocPoint": 22,
        "apr": 141.08106283014865,
        "apr2": 0,
        "chefVersion": "v1"
    },
    {
        "id": 6,
        "poolId": 6,
        "lpAddress": "0x5eeC60F348cB1D661E4A5122CF4638c7DB7A886e",
        "totalSupply": 9660167951859823097052,
        "totalStaked": 24015180501170435653,
        "totalStakedInUSD": 8984.603252526615,
        "totalRewardRate": 0.0,
        "allocPoint": 0,
        "apr": 0.0,
        "apr2": 0,
        "chefVersion": "v1"
    },
    {
        "id": 7,
        "poolId": 0,
        "lpAddress": "0x5eeC60F348cB1D661E4A5122CF4638c7DB7A886e",
        "totalSupply": 9660167951859823097052,
        "totalStaked": 9443308118847993568014,
        "totalStakedInUSD": 3532947.705101679,
        "totalRewardRate": 29030.4,
        "allocPoint": 4,
        "apr": 37.695094738843956,
        "apr2": 14.901307379444734,
        "chefVersion": "v2"
    },
    {
        "id": 8,
        "poolId": 1,
        "lpAddress": "0xd1654a7713617d41A8C9530Fb9B948d00e162194",
        "totalSupply": 959028956284232033461502,
        "totalStaked": 948628964690969373596579,
        "totalStakedInUSD": 6612513.329771283,
        "totalRewardRate": 217728.0,
        "allocPoint": 30,
        "apr": 151.04861624807728,
        "apr2": 7.961502243360305,
        "chefVersion": "v2"
    },
    {
        "id": 9,
        "poolId": 2,
        "lpAddress": "0xdF8CbF89ad9b7dAFdd3e37acEc539eEcC8c47914",
        "totalSupply": 66645802131649526533750884,
        "totalStaked": 65754965859030642635757134,
        "totalStakedInUSD": 2958751.4318820275,
        "totalRewardRate": 29030.4,
        "allocPoint": 4,
        "apr": 45.01047199036865,
        "apr2": 8.841532433987886,
        "chefVersion": "v2"
    },
    {
        "id": 10,
        "poolId": 3,
        "lpAddress": "0xa9eded3E339b9cd92bB6DEF5c5379d678131fF90",
        "totalSupply": 411921063582607590651482976,
        "totalStaked": 402849144380619123011829528,
        "totalStakedInUSD": 2692891.4437710647,
        "totalRewardRate": 29030.4,
        "allocPoint": 4,
        "apr": 49.45420238132367,
        "apr2": 9.71442677706284,
        "chefVersion": "v2"
    },
    {
        "id": 11,
        "poolId": 4,
        "lpAddress": "0x61C9E05d1Cdb1b70856c7a2c53fA9c220830633c",
        "totalSupply": 173633530493875816,
        "totalStaked": 171850179174762586,
        "totalStakedInUSD": 7251053.563549949,
        "totalRewardRate": 304819.2,
        "allocPoint": 42,
        "apr": 192.84582184949312,
        "apr2": 0.0,
        "chefVersion": "v2"
    },
    {
        "id": 12,
        "poolId": 5,
        "lpAddress": "0x6443532841a5279cb04420E61Cf855cBEb70dc8C",
        "totalSupply": 42841250488153356546277597,
        "totalStaked": 42811383127637237025057852,
        "totalStakedInUSD": 2311783.2544780946,
        "totalRewardRate": 29030.4,
        "allocPoint": 4,
        "apr": 57.60695696416163,
        "apr2": 0.0,
        "chefVersion": "v2"
    },
    {
        "id": 13,
        "poolId": 6,
        "lpAddress": "0x7be4a49AA41B34db70e539d4Ae43c7fBDf839DfA",
        "totalSupply": 23182973470420160509721179,
        "totalStaked": 23182879642978534020209283,
        "totalStakedInUSD": 2916747.031699056,
        "totalRewardRate": 29030.4,
        "allocPoint": 4,
        "apr": 45.658672831017675,
        "apr2": 0.0,
        "chefVersion": "v2"
    },
    {
        "id": 14,
        "poolId": 7,
        "lpAddress": "0x3dC236Ea01459F57EFc737A12BA3Bb5F3BFfD071",
        "totalSupply": 337561092499410912885793168,
        "totalStaked": 336681031922386189923915571,
        "totalStakedInUSD": 2755445.4538175343,
        "totalRewardRate": 29030.4,
        "allocPoint": 4,
        "apr": 48.331495100613225,
        "apr2": 0.0,
        "chefVersion": "v2"
    },
    {
        "id": 15,
        "poolId": 8,
        "lpAddress": "0x48887cEEA1b8AD328d5254BeF774Be91B90FaA09",
        "totalSupply": 344477353087931346232573323,
        "totalStaked": 205330696044123309353821176,
        "totalStakedInUSD": 1127637.5105458738,
        "totalRewardRate": 29030.4,
        "allocPoint": 4,
        "apr": 118.10071694646007,
        "apr2": 96.50011179230752,
        "chefVersion": "v2"
    },
    {
        "id": 16,
        "poolId": 9,
        "lpAddress": "0xd62f9ec4C4d323A0C111d5e78b77eA33A2AA862f",
        "totalSupply": 115314448677383504007950105,
        "totalStaked": 113883545315323643603908946,
        "totalStakedInUSD": 433469.72707253776,
        "totalRewardRate": 0.0,
        "allocPoint": 0,
        "apr": 0.0,
        "apr2": 1126.2150324369863,
        "chefVersion": "v2"
    }
]