[
    {
        "id": 0,
        "poolId": 0,
        "lpAddress": "0x63da4DB6Ef4e7C62168aB03982399F9588fCd198",
        "totalSupply": 126757385550992590043357501,
        "totalStaked": 126654783987232824140523093,
        "totalStakedInUSD": 57973118.65837703,
        "totalRewardRate": 332640.0,
        "allocPoint": 11,
        "apr": 27.15237600629741,
        "apr2": 0,
        "chefVersion": "v1"
    },
    {
        "id": 1,
        "poolId": 1,
        "lpAddress": "0x20F8AeFB5697B77E0BB835A8518BE70775cdA1b0",
        "totalSupply": 5529717183658442567147,
        "totalStaked": 5527685624145901634729,
        "totalStakedInUSD": 44466966.761034675,
        "totalRewardRate": 332640.0,
        "allocPoint": 11,
        "apr": 35.39948934518515,
        "apr2": 0,
        "chefVersion": "v1"
    },
    {
        "id": 2,
        "poolId": 2,
        "lpAddress": "0x03B666f3488a7992b2385B12dF7f35156d7b29cD",
        "totalSupply": 4407096486017422712313,
        "totalStaked": 4402930610415113011808,
        "totalStakedInUSD": 37322938.882875755,
        "totalRewardRate": 332640.0,
        "allocPoint": 11,
        "apr": 42.17534747222626,
        "apr2": 0,
        "chefVersion": "v1"
    },
    {
        "id": 3,
        "poolId": 3,
        "lpAddress": "0x2fe064B6c7D274082aa5d2624709bC9AE7D16C77",
        "totalSupply": 67708225469537,
        "totalStaked": 67674186896888,
        "totalStakedInUSD": 140421390.39434582,
        "totalRewardRate": 302400.0,
        "allocPoint": 10,
        "apr": 10.190806346586687,
        "apr2": 0,
        "chefVersion": "v1"
    },
    {
        "id": 4,
        "poolId": 4,
        "lpAddress": "0xbc8A244e8fb683ec1Fd6f88F3cc6E565082174Eb",
        "totalSupply": 369000551576814134684,
        "totalStaked": 368972307277128074635,
        "totalStakedInUSD": 58175843.46237741,
        "totalRewardRate": 332640.0,
        "allocPoint": 11,
        "apr": 27.0577583819293,
        "apr2": 0,
        "chefVersion": "v1"
    },
    {
        "id": 5,
        "poolId": 5,
        "lpAddress": "0x84b123875F0F36B966d0B6Ca14b31121bd9676AD",
        "totalSupply": 879703893721798758723480709,
        "totalStaked": 873375425915416113112482567,
        "totalStakedInUSD": 24535429.11550479,
        "totalRewardRate": 665280.0,
        "allocPoint": 22,
        "apr": 128.31305363843958,
        "apr2": 0,
        "chefVersion": "v1"
    },
    {
        "id": 6,
        "poolId": 6,
        "lpAddress": "0x5eeC60F348cB1D661E4A5122CF4638c7DB7A886e",
        "totalSupply": 9955764287002921993888,
        "totalStaked": 24015180501170435653,
        "totalStakedInUSD": 10422.816963929907,
        "totalRewardRate": 0.0,
        "allocPoint": 0,
        "apr": 0.0,
        "apr2": 0,
        "chefVersion": "v1"
    },
    {
        "id": 7,
        "poolId": 0,
        "lpAddress": "0x5eeC60F348cB1D661E4A5122CF4638c7DB7A886e",
        "totalSupply": 9955764287002921993888,
        "totalStaked": 9717582249627587185949,
        "totalStakedInUSD": 4217523.208491655,
        "totalRewardRate": 29030.4,
        "allocPoint": 4,
        "apr": 32.57283577726768,
        "apr2": 13.482704780150206,
        "chefVersion": "v2"
    },
    {
        "id": 8,
        "poolId": 1,
        "lpAddress": "0xd1654a7713617d41A8C9530Fb9B948d00e162194",
        "totalSupply": 917112984786991437453342,
        "totalStaked": 904910791798785274118361,
        "totalStakedInUSD": 6662927.21929362,
        "totalRewardRate": 217728.0,
        "allocPoint": 30,
        "apr": 154.6355149196473,
        "apr2": 8.534330100269855,
        "chefVersion": "v2"
    },
    {
        "id": 9,
        "poolId": 2,
        "lpAddress": "0xdF8CbF89ad9b7dAFdd3e37acEc539eEcC8c47914",
        "totalSupply": 71320226227570619434671018,
        "totalStaked": 69289019565343744037605795,
        "totalStakedInUSD": 4059245.880520967,
        "totalRewardRate": 29030.4,
        "allocPoint": 4,
        "apr": 33.842909471495894,
        "apr2": 8.363077075078001,
        "chefVersion": "v2"
    },
    {
        "id": 10,
        "poolId": 3,
        "lpAddress": "0xa9eded3E339b9cd92bB6DEF5c5379d678131fF90",
        "totalSupply": 480226260693081029802054056,
        "totalStaked": 472453696624310383536524604,
        "totalStakedInUSD": 3620773.5219072523,
        "totalRewardRate": 29030.4,
        "allocPoint": 4,
        "apr": 37.94125482464592,
        "apr2": 9.375838052308673,
        "chefVersion": "v2"
    },
    {
        "id": 11,
        "poolId": 4,
        "lpAddress": "0x61C9E05d1Cdb1b70856c7a2c53fA9c220830633c",
        "totalSupply": 181887924442817876,
        "totalStaked": 180397464038508863,
        "totalStakedInUSD": 7761182.627641452,
        "totalRewardRate": 304819.2,
        "allocPoint": 42,
        "apr": 185.8550846183338,
        "apr2": 0.0,
        "chefVersion": "v2"
    },
    {
        "id": 12,
        "poolId": 5,
        "lpAddress": "0x6443532841a5279cb04420E61Cf855cBEb70dc8C",
        "totalSupply": 46259015016331123825447427,
        "totalStaked": 45585818358222531660984594,
        "totalStakedInUSD": 3124182.0617415747,
        "totalRewardRate": 29030.4,
        "allocPoint": 4,
        "apr": 43.97205032936945,
        "apr2": 0.0,
        "chefVersion": "v2"
    },
    {
        "id": 13,
        "poolId": 6,
        "lpAddress": "0x7be4a49AA41B34db70e539d4Ae43c7fBDf839DfA",
        "totalSupply": 20877313004052512400927650,
        "totalStaked": 20874670821485207879449591,
        "totalStakedInUSD": 3247381.9067676896,
        "totalRewardRate": 29030.4,
        "allocPoint": 4,
        "apr": 42.30382960831141,
        "apr2": 0.0,
        "chefVersion": "v2"
    },
    {
        "id": 14,
        "poolId": 7,
        "lpAddress": "0x3dC236Ea01459F57EFc737A12BA3Bb5F3BFfD071",
        "totalSupply": 334957651089128070887603735,
        "totalStaked": 329666272923232576075911185,
        "totalStakedInUSD": 3490893.380005872,
        "totalRewardRate": 29030.4,
        "allocPoint": 4,
        "apr": 39.352875010116364,
        "apr2": 0.0,
        "chefVersion": "v2"
    },
    {
        "id": 15,
        "poolId": 8,
        "lpAddress": "0x48887cEEA1b8AD328d5254BeF774Be91B90FaA09",
        "totalSupply": 321954038085838899067255993,
        "totalStaked": 180966469721372227547577777,
        "totalStakedInUSD": 1157476.4158354618,
        "totalRewardRate": 29030.4,
        "allocPoint": 4,
        "apr": 118.68638442871061,
        "apr2": 96.0437315535905,
        "chefVersion": "v2"
    },
    {
        "id": 16,
        "poolId": 9,
        "lpAddress": "0xd62f9ec4C4d323A0C111d5e78b77eA33A2AA862f",
        "totalSupply": 225830463045872368636430265,
        "totalStaked": 224098016438726561387497793,
        "totalStakedInUSD": 1390969.783926309,
        "totalRewardRate": 0.0,
        "allocPoint": 0,
        "apr": 0.0,
        "apr2": 708.3028782882897,
        "chefVersion": "v2"
    }
]